mypandas/app.py
myfandas-0.0.1.dist-info/METADATA
myfandas-0.0.1.dist-info/WHEEL
myfandas-0.0.1.dist-info/top_level.txt
myfandas-0.0.1.dist-info/RECORD
