Metadata-Version: 2.1
Name: myfandas
Version: 0.0.1
Author: donghyeok
Classifier: Programming Language :: Python :: 3
Classifier: License :: OSI Approved :: MIT License
Classifier: Operating System :: OS Independent
Requires-Dist: pandas
